{
  "version": "4.5.6",
  "flags": {},
  "shapes": [
    {
      "label": "text",
      "line_color": null,
      "fill_color": null,
      "points": [
        [
          92.83122642441194,
          109.46022053459365
        ],
        [
          743.4688692678658,
          109.46022053459365
        ],
        [
          743.4688692678658,
          1219.8272096082144
        ],
        [
          92.83122642441194,
          1219.8272096082144
        ]
      ],
      "shape_type": "polygon",
      "flags": {}
    },
    {
      "label": "footer",
      "line_color": null,
      "fill_color": null,
      "points": [
        [
          397.7858415982115,
          1313.2636353952932
        ],
        [
          435.95851808440153,
          1313.2636353952932
        ],
        [
          435.95851808440153,
          1333.0287532061163
        ],
        [
          397.7858415982115,
          1333.0287532061163
        ]
      ],
      "shape_type": "polygon",
      "flags": {}
    }
  ],
  "lineColor": [
    0,
    255,
    0,
    128
  ],
  "fillColor": [
    255,
    0,
    0,
    128
  ],
  "imagePath": "220.png",
  "imageData": null,
  "imageHeight": 1403,
  "imageWidth": 834
}