{
  "version": "4.5.6",
  "flags": {},
  "shapes": [
    {
      "label": "text",
      "line_color": null,
      "fill_color": null,
      "points": [
        [
          149.10118296740222,
          545.6949462890625
        ],
        [
          902.7182559571178,
          545.6949462890625
        ],
        [
          902.7182559571178,
          955.709716796875
        ],
        [
          149.10118296740222,
          955.709716796875
        ]
      ],
      "shape_type": "polygon",
      "flags": {}
    },
    {
      "label": "title",
      "line_color": null,
      "fill_color": null,
      "points": [
        [
          380.41204194792545,
          368.43621826171875
        ],
        [
          678.6705102839408,
          368.43621826171875
        ],
        [
          678.6705102839408,
          413.372802734375
        ],
        [
          380.41204194792545,
          413.372802734375
        ]
      ],
      "shape_type": "polygon",
      "flags": {}
    },
    {
      "label": "text",
      "line_color": null,
      "fill_color": null,
      "points": [
        [
          149.80989411318208,
          1014.2575073242188
        ],
        [
          902.185955109556,
          1014.2575073242188
        ],
        [
          902.185955109556,
          1146.552490234375
        ],
        [
          149.80989411318208,
          1146.552490234375
        ]
      ],
      "shape_type": "polygon",
      "flags": {}
    }
  ],
  "lineColor": [
    0,
    255,
    0,
    128
  ],
  "fillColor": [
    255,
    0,
    0,
    128
  ],
  "imagePath": "D:\\MNBVC-layout-test\\15\\0550.pdf\\2.png",
  "imageData": null,
  "imageHeight": 1600,
  "imageWidth": 1050
}