{
  "version": "4.5.6",
  "flags": {},
  "shapes": [
    {
      "label": "text",
      "line_color": null,
      "fill_color": null,
      "points": [
        [
          261.3132736880827,
          226.60474839683334
        ],
        [
          1425.121993605502,
          226.60474839683334
        ],
        [
          1425.121993605502,
          1894.3337721719286
        ],
        [
          261.3132736880827,
          1894.3337721719286
        ]
      ],
      "shape_type": "polygon",
      "flags": {}
    },
    {
      "label": "header",
      "line_color": null,
      "fill_color": null,
      "points": [
        [
          1399.5056070964993,
          127.17314478580369
        ],
        [
          1432.2139087625367,
          127.17314478580369
        ],
        [
          1432.2139087625367,
          147.56569460824528
        ],
        [
          1399.5056070964993,
          147.56569460824528
        ]
      ],
      "shape_type": "polygon",
      "flags": {}
    }
  ],
  "lineColor": [
    0,
    255,
    0,
    128
  ],
  "fillColor": [
    255,
    0,
    0,
    128
  ],
  "imagePath": "D:\\MNBVC-layout-test\\17\\0513.pdf\\100.png",
  "imageData": null,
  "imageHeight": 2339,
  "imageWidth": 1653
}